Sakurajima/__init__.py
Sakurajima/api.py
Sakurajima/errors.py
Sakurajima/models/__init__.py
Sakurajima/models/base_models.py
Sakurajima/models/chronicle.py
Sakurajima/models/helper_models.py
Sakurajima/models/media.py
Sakurajima/models/notification.py
Sakurajima/models/recommendation.py
Sakurajima/models/relation.py
Sakurajima/models/stats.py
Sakurajima/models/user_models.py
Sakurajima/models/watchlist.py
Sakurajima/utils/__init__.py
Sakurajima/utils/decrypter_provider.py
Sakurajima/utils/downloader.py
Sakurajima/utils/episode_list.py
Sakurajima/utils/merger.py
Sakurajima/utils/misc.py
Sakurajima/utils/network.py
Sakurajima/utils/progress_tracker.py
sakurajima-0.3.1.dist-info/LICENSE.md
sakurajima-0.3.1.dist-info/METADATA
sakurajima-0.3.1.dist-info/WHEEL
sakurajima-0.3.1.dist-info/top_level.txt
sakurajima-0.3.1.dist-info/RECORD
