Metadata-Version: 2.1
Name: sakurajima
Version: 0.3.1
Summary: AniWatch.me API wrapper & downloader
Home-page: https://github.com/veselysps/Sakurajima
Author: NotMarek, Dhanraj Hira
Author-email: notmarek1337@gmail.com
License: MIT
Platform: UNKNOWN
Classifier: Programming Language :: Python :: 3
Classifier: License :: OSI Approved :: MIT License
Classifier: Operating System :: OS Independent
Requires-Python: >=3.6
Requires-Dist: requests (>=2.23.0)
Requires-Dist: pycryptodome (>=3.9.7)
Requires-Dist: m3u8 (>=0.6.0)
Requires-Dist: pathvalidate (>=2.3.0)
